dsff/VERSION.txt
dsff/__common__.py
dsff/__info__.py
dsff/__init__.py
dsff/arff.py
dsff/csv.py
dsff/dataset.py
dsff-1.0.7.dist-info/LICENSE
dsff-1.0.7.dist-info/METADATA
dsff-1.0.7.dist-info/WHEEL
dsff-1.0.7.dist-info/top_level.txt
dsff-1.0.7.dist-info/RECORD
