Metadata-Version: 2.1
Name: dsff
Version: 1.0.7
Summary: DataSet File Format (DSFF)
Author-email: Alexandre D'Hondt <alexandre.dhondt@gmail.com>
License: GNU GENERAL PUBLIC LICENSE
Project-URL: documentation, https://python-dsff.readthedocs.io/en/latest/?badge=latest
Project-URL: homepage, https://github.com/packing-box/python-dsff
Project-URL: issues, https://github.com/packing-box/python-dsff/issues
Project-URL: repository, https://github.com/packing-box/python-dsff
Keywords: python,programming,dataset-file-format,dsff
Classifier: Development Status :: 5 - Production/Stable
Classifier: Environment :: Console
Classifier: Intended Audience :: Developers
Classifier: Intended Audience :: Information Technology
Classifier: Intended Audience :: Other Audience
Classifier: License :: OSI Approved :: GNU General Public License v3 or later (GPLv3+)
Classifier: Programming Language :: Python :: 3
Classifier: Programming Language :: Python :: 3 :: Only
Classifier: Programming Language :: Python :: 3.8
Classifier: Programming Language :: Python :: 3.9
Classifier: Programming Language :: Python :: 3.10
Classifier: Programming Language :: Python :: 3.11
Classifier: Programming Language :: Python :: 3.12
Classifier: Topic :: Software Development :: Libraries :: Python Modules
Requires-Python: <4,>=3.8
License-File: LICENSE
Requires-Dist: openpyxl
